nat/meta/pypi.md
nat/plugins/a2a/__init__.py
nat/plugins/a2a/register.py
nat/plugins/a2a/auth/__init__.py
nat/plugins/a2a/auth/credential_service.py
nat/plugins/a2a/cli/__init__.py
nat/plugins/a2a/cli/commands.py
nat/plugins/a2a/client/__init__.py
nat/plugins/a2a/client/client_base.py
nat/plugins/a2a/client/client_config.py
nat/plugins/a2a/client/client_impl.py
nat/plugins/a2a/server/__init__.py
nat/plugins/a2a/server/agent_executor_adapter.py
nat/plugins/a2a/server/front_end_config.py
nat/plugins/a2a/server/front_end_plugin.py
nat/plugins/a2a/server/front_end_plugin_worker.py
nat/plugins/a2a/server/oauth_middleware.py
nat/plugins/a2a/server/register_frontend.py
nvidia_nat_a2a-1.5.0a20260130.dist-info/licenses/LICENSE.md
nvidia_nat_a2a-1.5.0a20260130.dist-info/METADATA
nvidia_nat_a2a-1.5.0a20260130.dist-info/WHEEL
nvidia_nat_a2a-1.5.0a20260130.dist-info/entry_points.txt
nvidia_nat_a2a-1.5.0a20260130.dist-info/top_level.txt
nvidia_nat_a2a-1.5.0a20260130.dist-info/RECORD
