Metadata-Version: 2.4
Name: nvidia-nat-a2a
Version: 1.5.0a20260130
Summary: Subpackage for A2A Protocol integration in NeMo Agent Toolkit
Author: NVIDIA Corporation
Maintainer: NVIDIA Corporation
License: Apache-2.0
Project-URL: documentation, https://docs.nvidia.com/nemo/agent-toolkit/latest/
Project-URL: source, https://github.com/NVIDIA/NeMo-Agent-Toolkit
Keywords: ai,rag,agents,a2a
Classifier: Programming Language :: Python
Classifier: Programming Language :: Python :: 3.11
Classifier: Programming Language :: Python :: 3.12
Classifier: Programming Language :: Python :: 3.13
Requires-Python: <3.14,>=3.11
License-File: LICENSE.md
Requires-Dist: nvidia-nat==v1.5.0a20260130
Requires-Dist: a2a-sdk<1.0.0,>=0.3.20
Dynamic: license-file
